<?xml version="1.0" encoding="utf-8" standalone="yes"?>
<imgdir name="1123.img">
    <imgdir name="QuestInfo">
        <string name="name" value="Tae Soo's Proof of Love" />
        <int name="area" value="44" />
        <string name="0" value="To receive a #t4031691#, go see Tae Soo." />
        <string name="1" value="Tae Soo asks that you prove your love by bringing him #b30 #t4000278#s#k.\n\n#i4000278##t4000278# #b#c4000278# / 30#k" />
        <string name="2" value="You received a Proof of Love from Tae Soo." />
    </imgdir>
    <imgdir name="Act">
        <imgdir name="0" />
        <imgdir name="1">
            <imgdir name="item">
                <imgdir name="0">
                    <int name="id" value="4000278" />
                    <int name="count" value="-30" />
                </imgdir>
                <imgdir name="1">
                    <int name="id" value="4031691" />
                    <int name="count" value="1" />
                </imgdir>
            </imgdir>
        </imgdir>
    </imgdir>
    <imgdir name="Check">
        <imgdir name="1">
            <int name="npc" value="2091003" />
            <imgdir name="item">
                <imgdir name="0">
                    <int name="id" value="4000278" />
                    <int name="count" value="30" />
                </imgdir>
            </imgdir>
        </imgdir>
        <imgdir name="0">
            <int name="npc" value="2091003" />
            <int name="infoNumber" value="1100" />
            <imgdir name="infoex">
                <imgdir name="0">
                    <string name="value" value="ing" />
                </imgdir>
            </imgdir>
            <imgdir name="item">
                <imgdir name="0">
                    <int name="id" value="4031691" />
                </imgdir>
            </imgdir>
            <int name="interval" value="0" />
        </imgdir>
    </imgdir>
</imgdir>