<?xml version="1.0" encoding="utf-8" standalone="yes"?>
<imgdir name="22557.img">
    <imgdir name="QuestInfo">
        <string name="name" value="Kidnapping of Camila" />
        <int name="area" value="7" />
        <int name="autoStart" value="1" />
        <string name="0" value="Chief Stan is calling you urgently... What could this be about?" />
        <string name="1" value="Chief Stan says that #p1012108#, who went out of town to pick strawberries, has been kidnapped by Golems. He asks that you go to Golem's Temple and rescue #p1012108#." />
        <string name="2" value="Fortunately, you were able to rescue #p1012108#, but what was that strange Golem?" />
    </imgdir>
    <imgdir name="Act">
        <imgdir name="0" />
        <imgdir name="1">
            <int name="exp" value="14500" />
            <imgdir name="sp">
                <imgdir name="0">
                    <int name="sp_value" value="1" />
                    <imgdir name="job">
                        <int name="0" value="2211" />
                    </imgdir>
                </imgdir>
            </imgdir>
        </imgdir>
    </imgdir>
    <imgdir name="Say">
        <imgdir name="0">
            <string name="0" value="Oh no! #p1012108# has been kidnapped by the Golems! I warned her to stay home, but she went out to pick strawberries! One of the Golems grabbed #p1012108# and disappeared into the Golem's Temple!" />
            <string name="1" value="We don't have much time! Please, hurry over to the #bGolem's Temple#k and rescue #b#p1012108##k!" />
            <imgdir name="stop" />
            <imgdir name="yes">
                <string name="0" value="I don't know how far the Golem went! You must hurry! Please, bring back #p1012108#!" />
            </imgdir>
            <imgdir name="no">
                <string name="0" value="This is no time for jokes! Quit stalling and accept my request!" />
            </imgdir>
        </imgdir>
        <imgdir name="1">
            <string name="0" value="You've brought #p1012108# back! Phew, what a relief. I never thought something so scary would happen." />
            <imgdir name="yes">
                <string name="0" value="I must come up with a plan. Just hold on a minute. I have to concentrate." />
            </imgdir>
            <imgdir name="stop">
                <imgdir name="default">
                    <string name="0" value="Why are you just standing there like that? Go into the #bGolem's Temple#k and rescue #b#p1012108##k! You can do it, can't you?! You must!" />
                </imgdir>
            </imgdir>
        </imgdir>
    </imgdir>
    <imgdir name="Check">
        <imgdir name="1">
            <int name="npc" value="1012003" />
            <int name="infoNumber" value="22598" />
            <imgdir name="infoex">
                <imgdir name="0">
                    <string name="value" value="2" />
                </imgdir>
            </imgdir>
        </imgdir>
        <imgdir name="0">
            <int name="npc" value="1012003" />
            <imgdir name="quest">
                <imgdir name="0">
                    <int name="id" value="22556" />
                    <int name="state" value="2" />
                </imgdir>
            </imgdir>
            <int name="lvmin" value="35" />
            <imgdir name="job">
                <int name="0" value="2200" />
                <int name="1" value="2210" />
                <int name="2" value="2211" />
                <int name="3" value="2212" />
                <int name="4" value="2213" />
                <int name="5" value="2214" />
                <int name="6" value="2215" />
                <int name="7" value="2216" />
                <int name="8" value="2217" />
                <int name="9" value="2218" />
            </imgdir>
            <int name="normalAutoStart" value="1" />
        </imgdir>
    </imgdir>
</imgdir>